yudown/__init__.py
yudown/__main__.py
yudown/cli.py
yudown/database.py
yudown/model.py
yudown/playlist.py
yudown/utils.py
yudown-0.6.0.dist-info/entry_points.txt
yudown-0.6.0.dist-info/WHEEL
yudown-0.6.0.dist-info/METADATA
yudown-0.6.0.dist-info/LICENSE
yudown-0.6.0.dist-info/RECORD
