Metadata-Version: 2.1
Name: yudown
Version: 0.6.0
Summary: This is a python script to download Youtube Media file
License: MIT
Author: TianaNanta
Author-email: andrianjakananta@gmail.com
Requires-Python: >=3.8,<4.0
Classifier: License :: OSI Approved :: MIT License
Classifier: Programming Language :: Python :: 3
Classifier: Programming Language :: Python :: 3.8
Classifier: Programming Language :: Python :: 3.9
Classifier: Programming Language :: Python :: 3.10
Classifier: Programming Language :: Python :: 3.11
Requires-Dist: pytube (>=12.1.2,<13.0.0)
Requires-Dist: tinydb (>=4.7.1,<5.0.0)
Requires-Dist: typer[all] (>=0.7.0,<0.8.0)
